pyOneNote/FileNode.py
pyOneNote/Header.py
pyOneNote/Main.py
pyOneNote/OneDocument.py
pyOneNote/__init__.py
pyOneNote-0.0.2.dist-info/METADATA
pyOneNote-0.0.2.dist-info/WHEEL
pyOneNote-0.0.2.dist-info/entry_points.txt
pyOneNote-0.0.2.dist-info/license
pyOneNote-0.0.2.dist-info/top_level.txt
pyOneNote-0.0.2.dist-info/RECORD
